afterthought/__init__.py
afterthought-0.5.0.dist-info/LICENSE
afterthought-0.5.0.dist-info/METADATA
afterthought-0.5.0.dist-info/WHEEL
afterthought-0.5.0.dist-info/RECORD
