Metadata-Version: 2.1
Name: afterthought
Version: 0.5.0
Summary: 
Author: Sharpz7
Author-email: adam.mcarthur62@gmail.com
Requires-Python: >=3.8,<4.0
Classifier: Programming Language :: Python :: 3
Classifier: Programming Language :: Python :: 3.8
Classifier: Programming Language :: Python :: 3.9
Classifier: Programming Language :: Python :: 3.10
Classifier: Programming Language :: Python :: 3.11
Classifier: Programming Language :: Python :: 3.12
Requires-Dist: debugpy (>=1.8.1,<2.0.0)
